pyisim/__init__.py
pyisim/auth.py
pyisim/exceptions.py
pyisim/response.py
pyisim/rest.py
pyisim/search.py
pyisim/soap.py
pyisim/utils.py
pyisim/entities/__init__.py
pyisim/entities/access.py
pyisim/entities/account.py
pyisim/entities/activity.py
pyisim/entities/group.py
pyisim/entities/organizational_container.py
pyisim/entities/person.py
pyisim/entities/provisioning_policy.py
pyisim/entities/request.py
pyisim/entities/role.py
pyisim/entities/service.py
pyisim/va/__init__.py
pyisim/va/auth.py
pyisim/va/configure/__init__.py
pyisim/va/configure/update_property.py
pyisim-0.3.1.dist-info/LICENSE
pyisim-0.3.1.dist-info/METADATA
pyisim-0.3.1.dist-info/WHEEL
pyisim-0.3.1.dist-info/top_level.txt
pyisim-0.3.1.dist-info/RECORD
