Metadata-Version: 2.1
Name: pyisim
Version: 0.3.1
Summary: Easy to use Python client for IBM Security Identity Manager (ISIM/ITIM) web services (SOAP and REST APIs) 
Home-page: https://github.com/cazdlt/pyisim
Author: Andrés Zamora
Author-email: cazdlt@gmail.com
License: MIT
Download-URL: https://github.com/cazdlt/pyisim/archive/v0.3.1.tar.gz
Keywords: isim,ibm-security,iam,itim
Platform: UNKNOWN
Classifier: Development Status :: 4 - Beta
Classifier: Intended Audience :: Developers
Classifier: Topic :: Software Development
Classifier: License :: OSI Approved :: MIT License
Classifier: Operating System :: OS Independent
Classifier: Programming Language :: Python :: 3.8
Requires-Python: >=3.8.0
Requires-Dist: requests (>=2.23.0)
Requires-Dist: zeep (>=3.4.0)
